document_ai/__init__.py
document_ai/base.py
document_ai/extractor.py
document_ai/formatter.py
document_ai/llm.py
document_ai/parser.py
document_ai/processer.py
document_ai/utils.py
document_ai/schemas/__init__.py
document_ai/schemas/core.py
document_ai/schemas/pdf/__init__.py
document_ai/schemas/pdf/digital.py
document_ai/schemas/pdf/scanned.py
document_ai/types/pdf/digital.py
document_ai/types/pdf/scanned.py
doc_intelligence-0.1.0.dist-info/METADATA
doc_intelligence-0.1.0.dist-info/WHEEL
doc_intelligence-0.1.0.dist-info/RECORD
