Metadata-Version: 2.4
Name: doc-intelligence
Version: 0.1.0
Summary: Document AI - Intelligent document processing and extraction
Requires-Python: >=3.10
Requires-Dist: google-genai>=1.57.0
Requires-Dist: loguru>=0.7.3
Requires-Dist: mkdocs-material>=9.7.1
Requires-Dist: mkdocs>=1.6.1
Requires-Dist: openai>=2.15.0
Requires-Dist: pdfplumber>=0.11.9
Requires-Dist: pre-commit>=4.5.1
Requires-Dist: pymupdf>=1.26.7
Requires-Dist: python-dotenv>=1.2.1
